gpt/__init__.py
gpt/openai/__init__.py
gpt/openai/chat_completion.py
kaar_gpt-0.1.0.dist-info/METADATA
kaar_gpt-0.1.0.dist-info/WHEEL
kaar_gpt-0.1.0.dist-info/RECORD
